pykalkan/__init__.py
pykalkan/adapter.py
pykalkan/enums.py
pykalkan/error_codes.py
pykalkan/exceptions.py
pykalkan/interface.py
pykalkan/C/__init__.py
pykalkan/C/lib_handle.py
tests/__init__.py
tests/main_test.py
pykalkan-1.2.0.dist-info/LICENSE
pykalkan-1.2.0.dist-info/METADATA
pykalkan-1.2.0.dist-info/WHEEL
pykalkan-1.2.0.dist-info/top_level.txt
pykalkan-1.2.0.dist-info/RECORD
