Metadata-Version: 2.1
Name: pykalkan
Version: 1.2.0
Summary: Адаптер(Python) для работы с ЭЦП РК
Author-email: Shalkarov Temirlan <shalqarov01@gmail.com>
Project-URL: Homepage, https://github.com/shalqarov/pykalkan
Project-URL: Bug Tracker, https://github.com/shalqarov/pykalkan/issues
Classifier: Programming Language :: Python :: 3
Classifier: License :: OSI Approved :: MIT License
Classifier: Operating System :: POSIX :: Linux
Requires-Python: >=3.7
License-File: LICENSE
